{
  "version": "v3",
  "title": "Forte Rocha",
  "tone": {
    "recommended": "D"
  },
  "score": {
    "stanzas": [
      {
        "type": "lyric",
        "code": "1",
        "text": [
          "[D]Forte Rocha é [F#m]Deus Sempi[E]ter[A]no;",
          "[Bm]Nos - [F#m]sa    [G]fé  [D/F#]só    [Em7]n´Ele se [A]fun[D]da;",
          "Seu amor celes[F#m]tial e pa[E]ter[A]no,",
          "[Bm]Na   [F#m]tri - [G]bu –[D/F#] la - [Em7]ção nos cir[A]cun[D]da.",
          "Do_astuto [E]tenta[A]dor [D]nos livra_o [G]Cria[Bm]dor e nos pro[E]te[A]ge;",
          "[G]Nada [B7]nós teme[Em]re - [F#]mos,",
          "[Bm]Pois [F#m] o    [G]In - [D/F#]vem - [Em7]cível nós [A]te[D]mos."
        ]
      },
      {
        "type": "lyric",
        "code": "2",
        "text": [
          "[D]Estará para [F#m]sempre per[E]di-[A]do",
          "[Bm]Quem [F#m]em    [G]si  [D/F#]so  -  [Em7]mente con[A]fi - [D]a,",
          "Mas será lá do [F#m]céu soco[E]rri[A]do,",
          "[Bm]Cren - [F#m]do    [G]em  [D/F#] Je  - [Em7]sus, nosso G[A]ui - [D]a.",
          "O Filho [E]do bom D[A]eus [D]é Defen[G]sor dos [Bm]Seus, é Rei da g[E]lór[A]ia;",
          "D[G]´Ele [B7]virtude [Em]te - [F#]mos,",
          "[Bm]E    [F#m]vi - [G]tó - [D/F#]ria   [Em7]alcança[A]rem[D]os."
        ]
      },
      {
        "type": "lyric",
        "code": "3",
        "text": [
          "[D]A Palavra, que[F#m] é nossa [E]Vi-[A]da,",
          "[Bm]De - [F#m]ve   s[G]er  [D/F#]por    [Em7]nós exal[A]ta - [D]da;",
          "É, também, nossa [F#m]firme Gua[E]ri-[A]da",
          "[Bm]Que  [F#m]não   [G]po -[D/F#] de   s[Em7]er abal[A]a - d[D]a.",
          "O mal vi[E]rá tent[A]ar  [D]a fim de [G]despo[Bm]jar os resga[E]ta-d[A]os, ",
          "[G]Mas te[B7]remos vi[Em]tó - [F#]ria, ",
          "[Bm]Pois [F#m] é   [G]nos - [D/F#]so_o  [Em7]reino e_a g[A]lór[D]ia."
        ]
      }
    ]
  }
}