{
  "version": "v1",
  "title": "Forte Rocha",
  "difficulty": 3,
  "tone": "D",
  "content": [
    "   D             F#m       E  A",
    "1. Forte Rocha é Deus Sempiterno;",
    "Bm    F#m   G   D/F#  Em7      A  D",
    "Nos - sa    fé  só    n´Ele se funda;",
    "              F#m      E  A",
    "Seu amor celestial e paterno,",
    "Bm   F#m   G   D/F#  Em7        A  D",
    "Na   tri - bu – la - ção nos circunda.",
    "          E    A   D           G   Bm           E A",
    "Do_astuto tentador nos livra_o Criador e nos protege;",
    "G    B7      Em   F#",
    "Nada nós temere - mos,",
    "Bm   F#m   G    D/F#  Em7       A D",
    "Pois  o    In - vem - cível nós temos.",
    "",
    "   D           F#m       E  A",
    "2. Estará para sempre perdi-do",
    "Bm   F#m   G   D/F#   Em7      A    D",
    "Quem em    si  so  -  mente confi - a,",
    "               F#m     E  A",
    "Mas será lá do céu socorrido,",
    "Bm     F#m   G   D/F#   Em7         A    D",
    "Cren - do    em   Je  - sus, nosso Gui - a.",
    "        E       A   D      G       Bm              E  A",
    "O Filho do bom Deus é Defensor dos Seus, é Rei da glória;",
    " G    B7      Em   F#",
    "D´Ele virtude te - mos,",
    "Bm   F#m  G    D/F#  Em7    A  D",
    "E    vi - tó - ria   alcançaremos.",
    "",
    "   D             F#m      E  A",
    "3. A Palavra, que é nossa Vi-da,",
    "Bm   F#m   G   D/F#   Em7     A    D",
    "De - ve   ser  por    nós exalta - da;",
    "                 F#m      E  A",
    "É, também, nossa firme Guari-da",
    "Bm   F#m   G   D/F#   Em7    A    D",
    "Que  não   po - de   ser abala - da.",
    "        E      A   D        G    Bm          E   A",
    "O mal virá tentar  a fim de despojar os resgata-dos, ",
    "G     B7      Em   F#",
    "Mas teremos vitó - ria, ",
    "Bm   F#m  G     D/F#  Em7        A  D",
    "Pois  é   nos - so_o  reino e_a glória."
  ]
}