{
  "code": "118",
  "version": "v3",
  "title": "Fiel Salvador é Jesus",
  "level": 3,
  "tone": {
    "original": "Db",
    "selected": "C"
  },
  "rhythm": "Valsa",
  "score": {
    "introduction": ["C", "F", "C", "G", "C"],
    "stanzas": [
      {
        "type": "lyric",
        "code": "1",
        "text": [
          "Fi[C]el Salvador é Je[F]sus, o meu [C]Rei,",
          "O meu poderoso Sen[G]hor;",
          "Es[C]tando em perigo, re[F]fúgio terei",
          "À [G]sombra do [G7]meu Reden[C]tor."
        ]
      },
      {
        "type": "chorus",
        "text": [
          "Es[G7]tou abrigado em [C]meu Salvador,",
          "Ne[Dm]nhum mal me [G7]pode atin[C]gir.",
          "Jesus tem por [C7]mim entra[F]nhável amor,",
          "A[G]mor que não posso expri[C]mir!",
          "A[G]mor que não [G7]posso expri[C]mir!"
        ]
      },
      {
        "type": "lyric",
        "code": "2",
        "text": [
          "Por [C]nome, Jesus, o Sen[F]hor, me cha[C]mou,",
          "Minh´alma preciosa Lhe [G]é;",
          "Com [C]Seu grande amor Ele [F]me circundou,",
          "Fir[G]mou-me na [G7]graça e na [C]fé."
        ]
      },
      {
        "type": "ref",
        "ref": "score.stanzas[1]"
      },
      {
        "type": "lyric",
        "code": "3",
        "text": [
          "A [C]fúria das águas ja[F]mais teme[C]rei,",
          "Jesus me dará Sua m[G]ão;",
          "Pas[C]sando no fogo, não [F]me queimarei,",
          "Com [G]Sua [G7]fiel prote[C]ção."
        ]
      },
      {
        "type": "ref",
        "ref": "score.stanzas[1]"
      }
    ]
  }
}
