{
  "version": "v1",
  "title": "Olha a Cristo, o Redentor",
  "difficulty": 3,
  "tone": "C",
  "content": [
    "   C              F      C",
    "1. Olha a Cristo, o Redentor,",
    "G                      C",
    "E não desprezes o Seu amor;",
    "                  F ",
    "Só por Seu sangue Deus dá mercê",
    "       C        F   G    C",
    "E salvação, que vêm pela fé.",
    "",
    "      C",
    "Por Jesus, receberás",
    "     G               C",
    "O perdão e_a paz dos céus;",
    "                  F ",
    "O Seu sangue livrará",
    "    C       G      C",
    "Tua alma da ira de Deus.",
    "",
    "   C              F      C",
    "2. Por Sua graça, o Salvador",
    "G                         C",
    "Quer conceder-te grande favor;",
    "              F ",
    "Ele te chama, vem sem tardar,",
    "           C      F  G   C",
    "Vem no Seu sangue te abrigar.",
    "",
    "   C                F         C",
    "3. Sem o Seu sangue não há perdão,",
    "G                           C",
    "Não há, com Deus, reconciliação;",
    "                 F ",
    "Das obras mortas limpo serás;",
    "         C       F  G    C",
    "Vida com glória_eterna terás."
  ]
}