{
  "code": "197",
  "version": "v3",
  "title": "Senhor, por Teu poder",
  "level": 4,
  "tone": {
    "original": "F",
    "selected": "E"
  },
  "rhythm": "Valsa",
  "score": {
    "introduction": ["E", "B7", "E"],
    "stanzas": [
      {
        "type": "lyric",
        "code": "1",
        "text": [
          "Sen[E]hor, por Teu poder, vem nos conceder",
          "Celestial ciência, ó Cria[B7]dor;",
          "Aq[E]ui nos encontramos para aprender",
          "A Tua sã doutrina, [A|↓↑]cheia [B7|↓]de a[E]mor."
        ]
      },
      {
        "type": "chorus",
        "text": [
          "A [B7]Tua igreja Te [E]roga, ó Deus:",
          "En[B7]via, do alto, Teu [E]Consolador;",
          "Em nossos corações desperta o fervor,",
          "Assim caminharemos [A|↓↑]rumo [B7|↓]aos c[E]éus."
        ]
      },
      {
        "type": "lyric",
        "code": "2",
        "text": [
          "Os [E]nossos corações conheces, ó Deus;",
          "Em comunhão Contigo estamos, Sen[B7]hor;",
          "Tu [E]prometeste, para todos os Teus,",
          "O Teu divino e santo [A|↓↑]Conso[B7|↓]la[E]dor."
        ]
      },
      {
        "type": "ref",
        "ref": "score.stanzas[1]"
      },
      {
        "type": "lyric",
        "code": "3",
        "text": [
          "Com [E]Teus conselhos santos vem ensinar",
          "Teus filhos muito amados, ó Cria[B7]dor;",
          "O [E]nosso entendimento vem renovar",
          "E faz-nos meditar no [A|↓↑]Teu gran[B7|↓]de a[E]mor."
        ]
      },
      {
        "type": "ref",
        "ref": "score.stanzas[1]"
      }
    ]
  }
}
