{
  "version": "v3",
  "title": "Oh! Marchai, soldados",
  "tone": {
    "recommended": "G"
  },
  "score": {
    "stanzas": [
      {
        "type": "lyric",
        "code": "1",
        "text": [
          "[G]Oh! Marchai, soldados, sois de Cristo!",
          "[C]Vós de[G]veis com [A]fé aqui marc[D]har;",
          "[G]Em justiça vós deveis an[C]dar",
          "Até en[G]trardes no e[D]terno [G]lar."
        ]
      },
      {
        "type": "chorus",
        "text": [
          "Oh! Mar[G]chai com valor,",
          "Ol[A]hai a Cristo, o Se[D]nhor,",
          "Pois só [G]d´Ele vos virá co[C]ragem",
          "Para avan[G]çardes com o [D]Reden[G]tor."
        ]
      },
      {
        "type": "lyric",
        "code": "2",
        "text": [
          "[G]Oh! Marchai, soldados, sois de Cristo!",
          "[C]A tor[G]menta [A]tendes que_enfren[D]tar,",
          "[G]Mas, bem firmes e sem duvi[C]dar,",
          "Resisti[G]reis sem nunca [D]vaci[G]lar."
        ]
      },
      {
        "type": "ref",
        "ref": "score.stanzas[1]"
      },
      {
        "type": "lyric",
        "code": "3",
        "text": [
          "[G]Oh! Marchai, soldados, sois de Cristo!",
          "[C]A vi[G]tória [A]vós ireis can[D]tar;",
          "[G]As primícias do eterno [C]lar,",
          "Jesus, o [G]Salvador, vos [D]faz pro[G]var."
        ]
      },
      {
        "type": "ref",
        "ref": "score.stanzas[1]"
      }
    ]
  }
}