{
  "code": "276",
  "version": "v3",
  "title": "Ó Senhor da glória",
  "tone": {
    "original": "Eb",
    "selected": "D"
  },
  "rhythm": "Canção",
  "score": {
    "introduction": ["D", "A", "D", "G", "D"],
    "stanzas": [
      {
        "type": "lyric",
        "code": "1",
        "text": ["[D]Ó Senhor da gló[A]ria, ", "Rei celesti[D]al,", "Sempre tens to[G]tal vi[D]tó[G]ria", "[D]Sobre [A7]todo o [D]mal."]
      },
      {
        "type": "lyric",
        "code": "2",
        "text": ["[D]Redentor celes[A]te,", "Fonte do sa[D]ber,", "Para nos re[G]mir, vi[D]es[G]te", "[D]Sobre a [A7]cruz mor[D]rer."]
      },
      {
        "type": "lyric",
        "code": "3",
        "text": ["[D]Tu nos libertas[A]te", "Da escravid[D]ão;", "Com Teu sangue [G]Tu pa[D]gas[G]te", "[D]Nossa [A7]transgres[D]são."]
      },
      {
        "type": "lyric",
        "code": "4",
        "text": ["[D]Nossa Fortale[A]za,", "Nossa Paz e [D]Luz,", "Nossa Glória [G]e Ri[D]que[G]za", "[D]És, Se[A7]nhor Jes[D]us."]
      }
    ]
  }
}
