{
  "version": "v2",
  "title": "Vem, Rei eterno",
  "tone": {
    "recommended": "C"
  },
  "score": {
    "stanzas": [
      {
        "type": "lyric",
        "code": "1",
        "verses": [
          {
            "chords": "C              G        C    F            C     G7 ",
            "lyrics": "A Tua obra de_amor contarei, ó glorioso Jesus;"
          },
          {
            "chords": "Am       E        F       C    D7                  G     G7 ",
            "lyrics": "Que os pecados perdoas, direi, e que do mundo_és a Luz."
          }
        ]
      },
      {
        "type": "chorus",
        "verses": [
          {
            "chords": "C    A7   Dm     G7           C",
            "lyrics": "Vem, Rei eterno, vem, Rei da glória,"
          },
          {
            "chords": "F       C    D    G   ",
            "lyrics": "Meu coração abençoar;"
          },
          {
            "chords": "C A7      Dm        G7     E7 ",
            "lyrics": "Unge meus lábios, e anunciarei"
          },
          {
            "chords": "F A7  Dm       G         C",
            "lyrics": "O Evangelho da graça sem par."
          }
        ]
      },
      {
        "type": "lyric",
        "code": "2",
        "verses": [
          {
            "chords": "C                 G         C     F                  C     G7 ",
            "lyrics": "Revelarás Teus mistérios, Senhor, a todo_aquele que crer;"
          },
          {
            "chords": "Am     E      F      C   D7               G     G7 ",
            "lyrics": "Pelo Espírito Consolador concederás Teu saber."
          }
        ]
      },
      {
        "type": "ref",
        "ref": "score.stanzas[1]"
      },
      {
        "type": "lyric",
        "code": "3",
        "verses": [
          {
            "chords": "C                G       C    F                 C     G7 ",
            "lyrics": "Por Tua graça me deste o bem, a paz, a vida, o_amor;"
          },
          {
            "chords": "Am      E        F        C   D7                    G     G7 ",
            "lyrics": "Certo darás esta graça também aos que Te buscam, Senhor."
          }
        ]
      },
      {
        "type": "ref",
        "ref": "score.stanzas[1]"
      }
    ]
  }
}