{
  "version": "v1",
  "title": "No céu, Senhor, no céu",
  "difficulty": 3,
  "tone": "A",
  "content": [
    "              A               E           A",
    "1. No céu, Senhor, no céu, Contigo lá em glória,",
    " D    E    A             E       B7   E    A ",
    "   No Teu eterno reino,_alegres, cantare - mos",
    "      F#        Bm     E         A    F#m ",
    "   Um hino glorioso, o hino da vitó - ria;",
    " D    E        A             D  Bm          E    A    A...",
    "   Senhor, Teu esplendor no céu    contemplare - mos.",
    "",
    "              A              E          A",
    "2. As portas, lá no céu, são pérolas preciosas",
    " D     E     A           E    B7  E  A",
    "   E_a praça da cidade_é ouro reluzente;",
    "      F#         Bm      E           A   F#m ",
    "   No céu é tudo puro; riquezas glorio - sas",
    " D    E    A           D   Bm        E  A    A...",
    "   Desfrutaremos com Jesus,    eternamente.",
    "",
    "          A          E          A",
    "3. O peregrino que almeja, no futuro,",
    " D    E   A            E     B7    E    A",
    "   Ir habitar com o Senhor Jesus, ama - do,",
    "      F#            Bm       E             A    F#m ",
    "   Procura ser mais santo, deseja ser mais pu - ro",
    " D   E     A             D   Bm            E  A    A...",
    "   E busca ser a Deus, o Pai,    mais consagrado.",
    "",
    "             A            E          A",
    "4. É glória_eterna para_o santo peregrino,",
    " D   E     A          E        B7   E    A",
    "   A celestial cidade por Deus prepara - da;",
    "      F#         Bm       E           A    F#m ",
    "   Em breve chegaremos ao triunfal desti - no,",
    " D   E       A          D   Bm         E    A    A...",
    "   Onde_há repouso do labor    e da jorna - da."
  ]
}