{
  "code": "389",
  "version": "v3",
  "title": "Cristo Jesus chama os Seus",
  "tone": {
    "original": "Bb",
    "selected": "A"
  },
  "rhythm": "Guarânia",
  "score": {
    "introduction": ["A", "E7", "A"],
    "stanzas": [
      {
        "type": "lyric",
        "code": "1",
        "text": [
          "[A]Cristo Jesus, o divino Pastor,",
          "[E7]Com doce voz, c[A]hama os Seus;",
          "Quer conduzi-los a Deus, Criador,",
          "[B7]Para viverem nos [E7]céus."
        ]
      },
      {
        "type": "chorus",
        "text": ["[A]Cristo Je[E7]sus", "Chama os S[A]eus", "[A7]Para a l[D]uz", "Que os g[A]uia ao [E7]reino dos c[A]éus."]
      },
      {
        "type": "lyric",
        "code": "2",
        "text": [
          "[A]Para lhes dar a herança eternal,",
          "[E7]Cristo Jesus c[A]hama os Seus;",
          "Ele é o Amigo que não tem igual,",
          "[B7]Ele é o Filho de [E7]Deus."
        ]
      },
      {
        "type": "ref",
        "ref": "score.stanzas[1]"
      },
      {
        "type": "lyric",
        "code": "3",
        "text": [
          "[A]Cristo Jesus, Sumo Sábio e Fiel,",
          "[E7]Com voz de amor, c[A]hama os Seus;",
          "Suas palavras, mais doces que o mel,",
          "[B7]Fazem que amemos a [E7]Deus."
        ]
      },
      {
        "type": "ref",
        "ref": "score.stanzas[1]"
      }
    ]
  }
}
